README.txt
setup.py
collective/__init__.py
collective.captchaforms.egg-info/PKG-INFO
collective.captchaforms.egg-info/SOURCES.txt
collective.captchaforms.egg-info/dependency_links.txt
collective.captchaforms.egg-info/entry_points.txt
collective.captchaforms.egg-info/namespace_packages.txt
collective.captchaforms.egg-info/not-zip-safe
collective.captchaforms.egg-info/paster_plugins.txt
collective.captchaforms.egg-info/requires.txt
collective.captchaforms.egg-info/top_level.txt
collective/captchaforms/__init__.py
collective/captchaforms/configure.zcml
collective/captchaforms/tests.py
collective/captchaforms/version.txt
collective/captchaforms/profiles/default/metadata.xml
collective/captchaforms/profiles/default/skins.xml
collective/captchaforms/skins/captchaforms/contact-info.cpt
collective/captchaforms/skins/captchaforms/contact-info.cpt.metadata
collective/captchaforms/skins/captchaforms/join_form.cpt
collective/captchaforms/skins/captchaforms/join_form.cpt.metadata
collective/captchaforms/skins/captchaforms/sendto_form.cpt
collective/captchaforms/skins/captchaforms/sendto_form.cpt.metadata
collective/captchaforms/skins/captchaforms/validate_captcha.vpy
docs/HISTORY.txt
docs/INSTALL.txt
docs/LICENSE.GPL
docs/LICENSE.txt