Metadata-Version: 1.0
Name: collective.captchaforms
Version: 0.1-20090814
Summary: Plone forms with captcha
Home-page: http://svn.plone.org/svn/collective/collective.captchaforms
Author: G. Gozadinos
Author-email: ggozad@qiweb.net
License: GPL
Platform: UNKNOWN
Classifier: Framework :: Plone
Classifier: Programming Language :: Python
Classifier: Topic :: Software Development :: Libraries :: Python Modules
